Metadata-Version: 1.1
Name: morepath-batching
Version: 0.1
Summary: A demo app for Morepath with record batching
Home-page: https://github.com/morepath/morepath_batching
Author: Morepath developers
Author-email: morepath@googlegroups.com
License: BSD
Keywords: morepath demo
Platform: UNKNOWN
Classifier: Intended Audience :: Developers
Classifier: Environment :: Web Environment
Classifier: License :: OSI Approved :: BSD License
Classifier: Topic :: Internet :: WWW/HTTP :: WSGI
Classifier: Programming Language :: Python :: 2
Classifier: Programming Language :: Python :: 2.7
Classifier: Programming Language :: Python :: 3
Classifier: Programming Language :: Python :: 3.3
Classifier: Programming Language :: Python :: 3.4
Classifier: Programming Language :: Python :: 3.5
